itk/Configuration/PhaseSymmetryConfig.py
itk/Configuration/PhaseSymmetry_snake_case.py
itk/PhaseSymmetryPython.py
itk/_PhaseSymmetryPython.so
itk/itkButterworthFilterFreqImageSourcePython.py
itk/itkLogGaborFreqImageSourcePython.py
itk/itkPhaseSymmetryImageFilterPython.py
itk/itkSinusoidImageSourcePython.py
itk/itkSinusoidSpatialFunctionPython.py
itk/itkSteerableFilterFreqImageSourcePython.py
itk_phasesymmetry-2.0.0.dist-info/METADATA
itk_phasesymmetry-2.0.0.dist-info/WHEEL
itk_phasesymmetry-2.0.0.dist-info/entry_points.txt
itk_phasesymmetry-2.0.0.dist-info/licenses/LICENSE
itk_phasesymmetry-2.0.0.dist-info/RECORD
